lkvpy/__init__.py
lkvpy/lkv.py
lkv-0.0.4.dist-info/LICENSE
lkv-0.0.4.dist-info/METADATA
lkv-0.0.4.dist-info/WHEEL
lkv-0.0.4.dist-info/top_level.txt
lkv-0.0.4.dist-info/RECORD
