Metadata-Version: 2.1
Name: lkv
Version: 0.0.4
Summary: this is a demo
Home-page: UNKNOWN
Author: lvkai
Author-email: 2427080101@qq.com
License: UNKNOWN
Platform: UNKNOWN
Classifier: Programming Language :: Python :: 3
Classifier: License :: OSI Approved :: MIT License
Classifier: Operating System :: OS Independent
